<?xml version="1.0" encoding="UTF-8" standalone="no" ?>
<layoutype>thumbnail</layoutype>

1a Temporada

<item>
<title>01 - O trabalho Nigeriano</title>
<link>http://media-br-am.crackle.com/1/e/r6/w02lf_480p.mp4</link>
<thumbnail>http://images-br-az.crackle.com/profiles/channels/100000815/OneSheetImage_220x330.jpg?ts=20150331131323</thumbnail>
<info>O CEO de um espaço aéreo pede a ajuda de Nate - um detetive privado especializado - para recuperar os desenhos de um avião que foram roubados pela empresa rival. O problema é que esses desenhos na verdade nunca pertenceram ao CEO.</info>
<genre>Ação</genre>
<fanart>http://simoncantan.com/wp-content/uploads/2013/11/Leverage.jpg</fanart>
</item>

<item>
<title>02 - O trabalho regresso à casa</title>
<link>http://media-br-am.crackle.com/1/e/r6/v02lf_480p.mp4</link>
<thumbnail>http://images-br-az.crackle.com/profiles/channels/100000815/OneSheetImage_220x330.jpg?ts=20150331131323</thumbnail>
<info>Leverage Consultoria & Associados volta serviço enquanto o time se reúne para ajudar um Reservista que foi ferido no Iraque por empreitoros militares privados. Para conseguir a ajuda que ele precisa mas não pode pagar o time investiga o porquê de ele ter sido atingido por fogo amigo.</info>
<genre>Ação</genre>
<fanart>http://simoncantan.com/wp-content/uploads/2013/11/Leverage.jpg</fanart>
</item>

<item>
<title>03 - O trabalho de dois cavalos</title>
<link>http://media-br-am.crackle.com/1/e/r6/u02lf_480p.mp4</link>
<thumbnail>http://images-br-az.crackle.com/profiles/channels/100000815/OneSheetImage_220x330.jpg?ts=20150331131323</thumbnail>
<info>Um investidor de Wall Street queima seu próprio estábulo para se livrar de seus cavalos que já não lucram tanto. O time da Leverage vai até Kentucky para ajudar o treinador de cavalos que perdeu tudo e está desolado.</info>
<genre>Ação</genre>
<fanart>http://simoncantan.com/wp-content/uploads/2013/11/Leverage.jpg</fanart>
</item>

<item>
<title>04 - O trabalho milagre</title>
<link>http://media-br-am.crackle.com/1/k/r6/j12lf_480p.mp4</link>
<thumbnail>http://images-br-az.crackle.com/profiles/channels/100000815/OneSheetImage_220x330.jpg?ts=20150331131323</thumbnail>
<info>Quando a Igreja central do antigo padre - e melhor amigo de infância - de Nate está prestes a ser demolida por um corretor imobiliário o time da Leverage precisa de um milagre para poder salvá-la.</info>
<genre>Ação</genre>
<fanart>http://simoncantan.com/wp-content/uploads/2013/11/Leverage.jpg</fanart>
</item>

<item>
<title>05 - O trabalho tiro banco</title>
<link>http://media-br-am.crackle.com/1/d/r6/s02lf_480p.mp4</link>
<thumbnail>http://images-br-az.crackle.com/profiles/channels/100000815/OneSheetImage_220x330.jpg?ts=20150331131323</thumbnail>
<info>Enquanto tenta desmascarar um juiz corrupto em uma cidadezinha deserta o time é pego no meio de um assalto a banco. Nate e Sophie acabam virando reféns assim como sua marca.</info>
<genre>Ação</genre>
<fanart>http://simoncantan.com/wp-content/uploads/2013/11/Leverage.jpg</fanart>
</item>

<item>
<title>06 - O trabalho cegonha</title>
<link>http://media-br-am.crackle.com/1/d/r6/t02lf_480p.mp4</link>
<thumbnail>http://images-br-az.crackle.com/profiles/channels/100000815/OneSheetImage_220x330.jpg?ts=20150331131323</thumbnail>
<info>A equipe da Leverage vai atrás de uma agência de adoção sérvia que está roubando dinheiro de casais americanos desesperados para adotarem órfãos da guerra.</info>
<genre>Ação</genre>
<fanart>http://simoncantan.com/wp-content/uploads/2013/11/Leverage.jpg</fanart>
</item>

<item>
<title>07 - O trabalho de casamento</title>
<link>http://media-br-am.crackle.com/1/n/r6/y12lf_480p.mp4</link>
<thumbnail>http://images-br-az.crackle.com/profiles/channels/100000815/OneSheetImage_220x330.jpg?ts=20150331131323</thumbnail>
<info>Para recuperar o dinheiro prometido à família de um homem inocente que acabou levando a culpa por um Mafioso o time da Leverage se passa por planejadores de casamento da filha do chefão.</info>
<genre>Ação</genre>
<fanart>http://simoncantan.com/wp-content/uploads/2013/11/Leverage.jpg</fanart>
</item>

<item>
<title>08 - O trabalho a milha alta</title>
<link>http://media-br-am.crackle.com/1/n/r6/z12lf_480p.mp4</link>
<thumbnail>http://images-br-az.crackle.com/profiles/channels/100000815/OneSheetImage_220x330.jpg?ts=20150331131323</thumbnail>
<info> O time da Leverage quer expor o esquema de um conglomerado e seu fertilizante tóxico que acabou resultando na morte de uma garota inocente. Mas o CEO colocou toda a evidência necessária em um avião para as Ilhas Cayman.</info>
<genre>Ação</genre>
<fanart>http://simoncantan.com/wp-content/uploads/2013/11/Leverage.jpg</fanart>
</item>

<item>
<title>09 - O trabalho de neve</title>
<link>http://media-br-am.crackle.com/1/o/r6/012lf_480p.mp4</link>
<thumbnail>http://images-br-az.crackle.com/profiles/channels/100000815/OneSheetImage_220x330.jpg?ts=20150331131323</thumbnail>
<info>O time da Leveage ajuda um Soldado da Guarda Nacional sitiado a levar justiça contra uma firma de construção inescrupulosa que barrou a sua casa.</info>
<genre>Ação</genre>
<fanart>http://simoncantan.com/wp-content/uploads/2013/11/Leverage.jpg</fanart>
</item>

<item>
<title>10 - O trabalho de 12 etapas</title>
<link>http://media-br-am.crackle.com/1/o/r6/312lf_480p.mp4</link>
<thumbnail>http://images-br-az.crackle.com/profiles/channels/100000815/OneSheetImage_220x330.jpg?ts=20150331131323</thumbnail>
<info>O time aponta para um investior que tenta trapacear uma caridade. Para descobrir onde o dinheiro está escondido eles enganam o financiador alcólatra para que ele entre em uma clínica de reabilitação.</info>
<genre>Ação</genre>
<fanart>http://simoncantan.com/wp-content/uploads/2013/11/Leverage.jpg</fanart>
</item>

<item>
<title>11 - O trabalho de jurado # 6</title>
<link>http://media-br-am.crackle.com/1/o/r6/112lf_480p.mp4</link>
<thumbnail>http://images-br-az.crackle.com/profiles/channels/100000815/OneSheetImage_220x330.jpg?ts=20150331131323</thumbnail>
<info>Quando o Parker comparece ao júri para manter a veracidade de um de seus pseudônimos ela nota algumas coisas estranhas no julgamento. Parece que alguém está tentando comprar um veredito favorável...</info>
<genre>Ação</genre>
<fanart>http://simoncantan.com/wp-content/uploads/2013/11/Leverage.jpg</fanart>
</item>

<item>
<title>12 - O trabalho de primeira David</title>
<link>http://media-br-am.crackle.com/1/o/r6/212lf_480p.mp4</link>
<thumbnail>http://images-br-az.crackle.com/profiles/channels/100000815/OneSheetImage_220x330.jpg?ts=20150331131323</thumbnail>
<info>Para o benefício de Nate o time vai atrás do CEO de uma companhia que negou o tratamento médico necessário ao filho de Nate e acabou culminando em sua morte.</info>
<genre>Ação</genre>
<fanart>http://simoncantan.com/wp-content/uploads/2013/11/Leverage.jpg</fanart>
</item>

<item>
<title>13 - O trabalho de segunda David</title>
<link>http://media-br-am.crackle.com/1/n/r6/w12lf_480p.mp4</link>
<thumbnail>http://images-br-az.crackle.com/profiles/channels/100000815/OneSheetImage_220x330.jpg?ts=20150331131323</thumbnail>
<info>Nate sai das sombras para desafiar diretamente Sterling e Blackpoole. Dessa vez ele irá roubar as duas estatuetas de David bem embaixo de seunariz. Mas o maior desafio de Nate é fazer com que seu time funcione novamente como uma equipe unida.</info>
<genre>Ação</genre>
<fanart>http://simoncantan.com/wp-content/uploads/2013/11/Leverage.jpg</fanart>
</item>












<?xml version="1.0" encoding="UTF-8" standalone="no" ?>
<layoutype>thumbnail</layoutype>

2a Temporada

<item>
<title>01 - O trabalho de resgate Beantown</title>
<link>http://media-br-am.crackle.com/1/q/r6/812lf_480p.mp4</link>
<thumbnail>http://images-br-az.crackle.com/profiles/channels/100000815/OneSheetImage_220x330.jpg?ts=20150331131323</thumbnail>
<info>Seis meses após conseguir se vingar de sua antiga empresa a nova e sóbria vida de Nate soofre uma guinada inesperada quando ele ajuda a vítima de um acidente de carro que estava prestes a desmascarar a fraude de um banco.</info>
<genre>Ação</genre>
<fanart>http://simoncantan.com/wp-content/uploads/2013/11/Leverage.jpg</fanart>
</item>

<item>
<title>02 - O trabalho de bater para fora</title>
<link>http://media-br-am.crackle.com/1/p/r6/712lf_480p.mp4</link>
<thumbnail>http://images-br-az.crackle.com/profiles/channels/100000815/OneSheetImage_220x330.jpg?ts=20150331131323</thumbnail>
<info>O time da Leverage vai até Nebraska para poder desmascarar um promoter trapaceiro de artes marciais e fazer como que ele abra mão de seu dinheiro e sua liga de luta.</info>
<genre>Ação</genre>
<fanart>http://simoncantan.com/wp-content/uploads/2013/11/Leverage.jpg</fanart>
</item>

<item>
<title>03 - O trabalho de ordem 23</title>
<link>http://media-br-am.crackle.com/1/p/r6/612lf_480p.mp4</link>
<thumbnail>http://images-br-az.crackle.com/profiles/channels/100000815/OneSheetImage_220x330.jpg?ts=20150331131323</thumbnail>
<info>Para fazer com que um ladrão convicto revele o esconderijo de seu dinheiro o time da Leverage rouba o hospital no qual ele está confinado e finge uma doença coletiva.</info>
<genre>Ação</genre>
<fanart>http://simoncantan.com/wp-content/uploads/2013/11/Leverage.jpg</fanart>
</item>

<item>
<title>04 - O trabalho padrinhos mágicos</title>
<link>http://media-br-am.crackle.com/1/p/r6/512lf_480p.mp4</link>
<thumbnail>http://images-br-az.crackle.com/profiles/channels/100000815/OneSheetImage_220x330.jpg?ts=20150331131323</thumbnail>
<info>O time tenta vencer um inescrupuloso investidor bancário ao roubar a escola de seu enteado enquanto Sophie e Eliot posam como os "padrinhos mágicos" do menino.</info>
<genre>Ação</genre>
<fanart>http://simoncantan.com/wp-content/uploads/2013/11/Leverage.jpg</fanart>
</item>

<item>
<title>05 - O trabalho de três dias do caçador</title>
<link>http://media-br-am.crackle.com/1/p/r6/412lf_480p.mp4</link>
<thumbnail>http://images-br-az.crackle.com/profiles/channels/100000815/OneSheetImage_220x330.jpg?ts=20150331131323</thumbnail>
<info>Sophie e Nate trocam de lugar enquanto o time arma para um tabloide com uma história falsa sobre esquemas do governo. Quando seu alvo começa a acreditar na história problemas sérios começam a aparecer.</info>
<genre>Ação</genre>
<fanart>http://simoncantan.com/wp-content/uploads/2013/11/Leverage.jpg</fanart>
</item>

<item>
<title>06 - O trabalho cartola</title>
<link>http://media-br-am.crackle.com/1/d/r6/r02lf_480p.mp4</link>
<thumbnail>http://images-br-az.crackle.com/profiles/channels/100000815/OneSheetImage_220x330.jpg?ts=20150331131323</thumbnail>
<info>O time se infiltra em uma Companhia que vende comida estragada enquanto se passam por mágicos.</info>
<genre>Ação</genre>
<fanart>http://simoncantan.com/wp-content/uploads/2013/11/Leverage.jpg</fanart>
</item>

<item>
<title>07 - O trabalho de Two Live Crew</title>
<link>http://media-br-am.crackle.com/1/c/r6/n02lf_480p.mp4</link>
<thumbnail>http://images-br-az.crackle.com/profiles/channels/100000815/OneSheetImage_220x330.jpg?ts=20150331131323</thumbnail>
<info>É ladrão versus ladrão enquanto o time Leverage sai contra outraequipe - comandada por um antigo "amigo" de Sophie - para recuperarem uma pintura orubada.</info>
<genre>Ação</genre>
<fanart>http://simoncantan.com/wp-content/uploads/2013/11/Leverage.jpg</fanart>
</item>

<item>
<title>08 - O trabalho do homem do gelo</title>
<link>http://media-br-am.crackle.com/1/c/r6/o02lf_480p.mp4</link>
<thumbnail>http://images-br-az.crackle.com/profiles/channels/100000815/OneSheetImage_220x330.jpg?ts=20150331131323</thumbnail>
<info>Hardison está disfarçado enquanto o time - menos Sophie - se envolve na venda de um diamante.</info>
<genre>Ação</genre>
<fanart>http://simoncantan.com/wp-content/uploads/2013/11/Leverage.jpg</fanart>
</item>

<item>
<title>09 - O trabalho herdeiro perdido</title>
<link>http://media-br-am.crackle.com/1/c/r6/p02lf_480p.mp4</link>
<thumbnail>http://images-br-az.crackle.com/profiles/channels/100000815/OneSheetImage_220x330.jpg?ts=20150331131323</thumbnail>
<info>O time Levarage mira em uma advogada harlatã enquanto ela tenta roubar a fortuna de seu cliente. Ao tentar se apossar do dinheiro da herança que estava prometido a uma caridade Parker finge ser a filha desaparecida do cliente e se passa por sua herdeira.</info>
<genre>Ação</genre>
<fanart>http://simoncantan.com/wp-content/uploads/2013/11/Leverage.jpg</fanart>
</item>

<item>
<title>10 - O trabalho de pista</title>
<link>http://media-br-am.crackle.com/1/d/r6/q02lf_480p.mp4</link>
<thumbnail>http://images-br-az.crackle.com/profiles/channels/100000815/OneSheetImage_220x330.jpg?ts=20150331131323</thumbnail>
<info> O time entra na indústria da moda para enganar o casal dono de uma empresa de roupas enquanto tentam se ajusat com seu mais novo membro.</info>
<genre>Ação</genre>
<fanart>http://simoncantan.com/wp-content/uploads/2013/11/Leverage.jpg</fanart>
</item>

<item>
<title>11 - O trabalho garrafa</title>
<link>http://media-br-am.crackle.com/1/b/r6/i02lf_480p.mp4</link>
<thumbnail>http://images-br-az.crackle.com/profiles/channels/100000815/OneSheetImage_220x330.jpg?ts=20150331131323</thumbnail>
<info>Quando um agiota tenta se apossar do Pub do McRory o time Leverage ao famoso truque do fio com pouco mais de uma hora para conseguirem se dar bem.</info>
<genre>Ação</genre>
<fanart>http://simoncantan.com/wp-content/uploads/2013/11/Leverage.jpg</fanart>
</item>

<item>
<title>12 - O trabalho de mercado Zanzibar</title>
<link>http://media-br-am.crackle.com/1/b/r6/j02lf_480p.mp4</link>
<thumbnail>http://images-br-az.crackle.com/profiles/channels/100000815/OneSheetImage_220x330.jpg?ts=20150331131323</thumbnail>
<info>Ex-esposa de Nate Maggie é presa por roubar uma joalheria em Kiev e o time precisa trabalhar com um antigo adversário para conseguir salvá-la.</info>
<genre>Ação</genre>
<fanart>http://simoncantan.com/wp-content/uploads/2013/11/Leverage.jpg</fanart>
</item>

<item>
<title>13 - O trabalho futuro</title>
<link>http://media-br-am.crackle.com/1/b/r6/k02lf_480p.mp4</link>
<thumbnail>http://images-br-az.crackle.com/profiles/channels/100000815/OneSheetImage_220x330.jpg?ts=20150331131323</thumbnail>
<info>O time vai em busca de um charlatão se passando por vidente mas acaba encontrando problema quando um ex-cliente rapta o cara para que ele adivinhe a localização de um ouro roubado.</info>
<genre>Ação</genre>
<fanart>http://simoncantan.com/wp-content/uploads/2013/11/Leverage.jpg</fanart>
</item>

<item>
<title>14 - O trabalho de três greves</title>
<link>http://media-br-am.crackle.com/1/b/r6/l02lf_480p.mp4</link>
<thumbnail>http://images-br-az.crackle.com/profiles/channels/100000815/OneSheetImage_220x330.jpg?ts=20150331131323</thumbnail>
<info>Patrick Bonanno da Polícia de Massachussets é baleado enquanto tenta derrotar um prefeito corrupto então o time toma a frente para terminar o que ele começou.</info>
<genre>Ação</genre>
<fanart>http://simoncantan.com/wp-content/uploads/2013/11/Leverage.jpg</fanart>
</item>

<item>
<title>15 - O trabalho de Falcão Maltês</title>
<link>http://media-br-am.crackle.com/1/c/r6/m02lf_480p.mp4</link>
<thumbnail>http://images-br-az.crackle.com/profiles/channels/100000815/OneSheetImage_220x330.jpg?ts=20150331131323</thumbnail>
<info>Com Sterling o FBI e todo mundo que carrega um distintivo os procurando o time Leverage se esconde para poder armar um plano que destrua o político corrupto e seu parceiro atirador.</info>
<genre>Ação</genre>
<fanart>http://simoncantan.com/wp-content/uploads/2013/11/Leverage.jpg</fanart>
</item>













<?xml version="1.0" encoding="UTF-8" standalone="no" ?>
<layoutype>thumbnail</layoutype>

3a Temporada

<item>
<title>01 - O trabalho de casa de detenção</title>
<link>http://media-br-am.crackle.com/1/a/r6/h02lf_480p.mp4</link>
<thumbnail>http://images-br-az.crackle.com/profiles/channels/100000815/OneSheetImage_220x330.jpg?ts=20150331131323</thumbnail>
<info>Enquanto o time trabalha para libertar Nate da cadeia ele precisa derrotar um diretor corrupto e libertar um homem inocente.</info>
<genre>Ação</genre>
<fanart>http://simoncantan.com/wp-content/uploads/2013/11/Leverage.jpg</fanart>
</item>

<item>
<title>02 - O trabalho reunião</title>
<link>http://media-br-am.crackle.com/1/_/n6/c02lf_480p.mp4</link>
<thumbnail>http://images-br-az.crackle.com/profiles/channels/100000815/OneSheetImage_220x330.jpg?ts=20150331131323</thumbnail>
<info>Para descobrir uma senha o time se infiltra em uma reunião de ensino médio para conseguirem enganar um magnata imoral do software responsável pelo departamento de TI do Machado do Mal.</info>
<genre>Ação</genre>
<fanart>http://simoncantan.com/wp-content/uploads/2013/11/Leverage.jpg</fanart>
</item>

<item>
<title>03 - O trabalho interno</title>
<link>http://media-br-am.crackle.com/1/n/r6/v12lf_480p.mp4</link>
<thumbnail>http://images-br-az.crackle.com/profiles/channels/100000815/OneSheetImage_220x330.jpg?ts=20150331131323</thumbnail>
<info>Quando Parker fica presa em uma locação desconhecida enquanto tenta roubar algo a pedido de seu mentor o time Leverage precisa correr contra o tempo para encontrá-la e libertá-la.</info>
<genre>Ação</genre>
<fanart>http://simoncantan.com/wp-content/uploads/2013/11/Leverage.jpg</fanart>
</item>

<item>
<title>04 - O trabalho Scheherazade</title>
<link>http://media-br-am.crackle.com/1/m/r6/u12lf_480p.mp4</link>
<thumbnail>http://images-br-az.crackle.com/profiles/channels/100000815/OneSheetImage_220x330.jpg?ts=20150331131323</thumbnail>
<info>Para roubarem o fundo de um cleptocrata africano o time Leverage precisa cronometrar seu golpe em função de uma sinfonia ali perto.</info>
<genre>Ação</genre>
<fanart>http://simoncantan.com/wp-content/uploads/2013/11/Leverage.jpg</fanart>
</item>

<item>
<title>05 - O trabalho em dupla ocultação</title>
<link>http://media-br-am.crackle.com/1/m/r6/t12lf_480p.mp4</link>
<thumbnail>http://images-br-az.crackle.com/profiles/channels/100000815/OneSheetImage_220x330.jpg?ts=20150331131323</thumbnail>
<info>Nate e o time dão um golpe em uma empresa farmacêutica que está desenvolvendo um remédio que poderia matar milhares de pessoas.</info>
<genre>Ação</genre>
<fanart>http://simoncantan.com/wp-content/uploads/2013/11/Leverage.jpg</fanart>
</item>

<item>
<title>06 - O trabalho de estúdio</title>
<link>http://media-br-am.crackle.com/1/l/r6/q12lf_480p.mp4</link>
<thumbnail>http://images-br-az.crackle.com/profiles/channels/100000815/OneSheetImage_220x330.jpg?ts=20150331131323</thumbnail>
<info>As coisas se complicam quando Elliot posa como um cantor de country para dar o truque em um executivo da indústria fonográfica mas acaba saindo com um artista falso.</info>
<genre>Ação</genre>
<fanart>http://simoncantan.com/wp-content/uploads/2013/11/Leverage.jpg</fanart>
</item>

<item>
<title>07 - O trabalho de pesca ida</title>
<link>http://media-br-am.crackle.com/1/m/r6/r12lf_480p.mp4</link>
<thumbnail>http://images-br-az.crackle.com/profiles/channels/100000815/OneSheetImage_220x330.jpg?ts=20150331131323</thumbnail>
<info>O time tenta desmascarar um coletor de dívidas que fica enganando cidadãos inocentes sem sabr que o cara é apoiado por uma milícia poderosa.</info>
<genre>Ação</genre>
<fanart>http://simoncantan.com/wp-content/uploads/2013/11/Leverage.jpg</fanart>
</item>

<item>
<title>08 - O trabalho impulso</title>
<link>http://media-br-am.crackle.com/1/m/r6/s12lf_480p.mp4</link>
<thumbnail>http://images-br-az.crackle.com/profiles/channels/100000815/OneSheetImage_220x330.jpg?ts=20150331131323</thumbnail>
<info>Nate e o time se infiltram em uma gangue perigosíssima de assaltantes de carro para tentarem desmascarar um vendedor trambiqueiro.</info>
<genre>Ação</genre>
<fanart>http://simoncantan.com/wp-content/uploads/2013/11/Leverage.jpg</fanart>
</item>

<item>
<title>09 - O trabalho de três cartas Monte</title>
<link>http://media-br-am.crackle.com/1/l/r6/p12lf_480p.mp4</link>
<thumbnail>http://images-br-az.crackle.com/profiles/channels/100000815/OneSheetImage_220x330.jpg?ts=20150331131323</thumbnail>
<info>Um velho inimigo complica as coisas para Nate e sua equipe enquanto eles tentam ajudar vários empresários pequenos que foram enganados a participar de um crime.</info>
<genre>Ação</genre>
<fanart>http://simoncantan.com/wp-content/uploads/2013/11/Leverage.jpg</fanart>
</item>

<item>
<title>10 - O trabalho subterrâneo</title>
<link>http://media-br-am.crackle.com/1/_/n6/d02lf_480p.mp4</link>
<thumbnail>http://images-br-az.crackle.com/profiles/channels/100000815/OneSheetImage_220x330.jpg?ts=20150331131323</thumbnail>
<info>Nate e o time investigam um acidente fatal em uma mina e acavam descobrindo muito mais coisa do que as práticas ilegais dali.</info>
<genre>Ação</genre>
<fanart>http://simoncantan.com/wp-content/uploads/2013/11/Leverage.jpg</fanart>
</item>

<item>
<title>11 - O trabalho Roshomon</title>
<link>http://media-br-am.crackle.com/1/a/r6/e02lf_480p.mp4</link>
<thumbnail>http://images-br-az.crackle.com/profiles/channels/100000815/OneSheetImage_220x330.jpg?ts=20150331131323</thumbnail>
<info>Cada membro do time relembra a história de um artefato que todos eles tentaram roubar na mesma noite cinco anos atrás.</info>
<genre>Ação</genre>
<fanart>http://simoncantan.com/wp-content/uploads/2013/11/Leverage.jpg</fanart>
</item>

<item>
<title>12 - O trabalho do Rei George</title>
<link>http://media-br-am.crackle.com/1/a/r6/f02lf_480p.mp4</link>
<thumbnail>http://images-br-az.crackle.com/profiles/channels/100000815/OneSheetImage_220x330.jpg?ts=20150331131323</thumbnail>
<info>Partes do passado de Sophie complicam um trabalho em Londres quando o time tenta expor um traficante de antiguidades que usa trabalho escravo de crianças no processo.</info>
<genre>Ação</genre>
<fanart>http://simoncantan.com/wp-content/uploads/2013/11/Leverage.jpg</fanart>
</item>

<item>
<title>13 - O trabalho de depois da manhã</title>
<link>http://media-br-am.crackle.com/1/a/r6/g02lf_480p.mp4</link>
<thumbnail>http://images-br-az.crackle.com/profiles/channels/100000815/OneSheetImage_220x330.jpg?ts=20150331131323</thumbnail>
<info>Um truque contra um financiador imundo pode ser a chave para que o time encontre Damien Moreau.</info>
<genre>Ação</genre>
<fanart>http://simoncantan.com/wp-content/uploads/2013/11/Leverage.jpg</fanart>
</item>

<item>
<title>14 - O trabalho de Ho Ho Ho</title>
<link>http://media-br-am.crackle.com/1/_/n6/a02lf_480p.mp4</link>
<thumbnail>http://images-br-az.crackle.com/profiles/channels/100000815/OneSheetImage_220x330.jpg?ts=20150331131323</thumbnail>
<info>O time entra numa fria quando tenta recuperar presentes de Natal para uma caridade e acabam encontrando um velho inimigo.</info>
<genre>Ação</genre>
<fanart>http://simoncantan.com/wp-content/uploads/2013/11/Leverage.jpg</fanart>
</item>

<item>
<title>15 - O trabalho do Big Bang</title>
<link>http://media-br-am.crackle.com/1/_/n6/b02lf_480p.mp4</link>
<thumbnail>http://images-br-az.crackle.com/profiles/channels/100000815/OneSheetImage_220x330.jpg?ts=20150331131323</thumbnail>
<info>O time se infiltra no laboratório de pesquisa de um Departamento de Defesa para conseguirem parar Damien Moreau o vilão que eles têm tentado capturar durante toda a temporada.</info>
<genre>Ação</genre>
<fanart>http://simoncantan.com/wp-content/uploads/2013/11/Leverage.jpg</fanart>
</item>

<item>
<title>16 - O trabalho de San Lorenzo</title>
<link>http://media-br-am.crackle.com/1/-/n6/9z2lf_480p.mp4</link>
<thumbnail>http://images-br-az.crackle.com/profiles/channels/100000815/OneSheetImage_220x330.jpg?ts=20150331131323</thumbnail>
<info>O time segue Moreau até San Lorenzo e descobrem que o cara é o atual conselheiro do Presidente.</info>
<genre>Ação</genre>
<fanart>http://simoncantan.com/wp-content/uploads/2013/11/Leverage.jpg</fanart>
</item>


































